sherlockeys.py
sherlockeys-0.1.0.dist-info/entry_points.txt
sherlockeys-0.1.0.dist-info/WHEEL
sherlockeys-0.1.0.dist-info/METADATA
sherlockeys-0.1.0.dist-info/RECORD
