Metadata-Version: 2.1
Name: sherlockeys
Version: 0.1.0
Summary: Sherlockeys is a usefull tool for pen-tester. It can quickly try to discover if a given api key works against the most common saas applications.
License: Apache 2.0
Author: s2b1n0
Author-email: joao.nsabino@gmail.com
Requires-Python: >=3.8,<4.0
Classifier: License :: Other/Proprietary License
Classifier: Programming Language :: Python :: 3
Classifier: Programming Language :: Python :: 3.10
Classifier: Programming Language :: Python :: 3.8
Classifier: Programming Language :: Python :: 3.9
Requires-Dist: colorama (>=0.4.5,<0.5.0)
Requires-Dist: requests (>=2.28.1,<3.0.0)
Requires-Dist: validators (>=0.20.0,<0.21.0)
